fk_utils/__init__.py
fk_utils/cache/__init__.py
fk_utils/cache/redis.py
fk_utils/config.py
fk_utils/envs/__init__.py
fk_utils/envs/aws/__init__.py
fk_utils/envs/aws/parameters.py
fk_utils/envs/aws/secrets.py
fk_utils/exceptions/__init__.py
fk_utils/exceptions/custom_http_exception.py
fk_utils/exceptions/custom_http_exception.pyi
fk_utils/logging/__init__.py
fk_utils/logging/fastapi/__init__.py
fk_utils/logging/fastapi/logging.py
fk_utils/middlewares/__init__.py
fk_utils/middlewares/django/__init__.py
fk_utils/middlewares/django/handler.py
fk_utils/middlewares/django/sql_middleware.py
fk_utils/middlewares/fastapi/__init__.py
fk_utils/middlewares/fastapi/error_middleware.py
fk_utils/middlewares/fastapi/i18n.py
fk_utils/middlewares/fastapi/language_middleware.py
fk_utils/middlewares/fastapi/sql_middleware.py
fk_utils/middlewares/flask/__init__.py
fk_utils/middlewares/flask/handler.py
fk_utils/middlewares/flask/sql_middleware.py
fk_utils/py.typed
fk_utils/traces/__init__.py
fk_utils/traces/opentelemetry/__init__.py
fk_utils/traces/opentelemetry/django/__init__.py
fk_utils/traces/opentelemetry/django/trace.py
fk_utils/traces/opentelemetry/fastapi/__init__.py
fk_utils/traces/opentelemetry/fastapi/aws_lambda/__init__.py
fk_utils/traces/opentelemetry/fastapi/aws_lambda/trace.py
fk_utils/traces/opentelemetry/fastapi/trace.py
fk_utils/traces/opentelemetry/flask/__init__.py
fk_utils/traces/opentelemetry/flask/trace.py
fk_util_tools-0.2.0.dist-info/LICENSE
fk_util_tools-0.2.0.dist-info/METADATA
fk_util_tools-0.2.0.dist-info/WHEEL
fk_util_tools-0.2.0.dist-info/RECORD
