Metadata-Version: 2.3
Name: fk_util_tools
Version: 0.2.0
Summary: This repository provides utility tools and common functions for FK projects, including helpers for configuration, logging, middleware, AWS integration, and OpenTelemetry instrumentation for Python web frameworks.
License: MIT
Author: Steven Santacruz Garcia
Author-email: steven.santacruz@finkargo.com
Requires-Python: >=3.10,<4.0
Classifier: License :: OSI Approved :: MIT License
Classifier: Programming Language :: Python :: 3
Classifier: Programming Language :: Python :: 3.10
Classifier: Programming Language :: Python :: 3.11
Classifier: Programming Language :: Python :: 3.12
Classifier: Programming Language :: Python :: 3.13
Requires-Dist: boto3 (>=1.40.26,<2.0.0)
Requires-Dist: opentelemetry-api (>=1.36.0,<2.0.0)
Requires-Dist: opentelemetry-exporter-jaeger (>=1.21.0,<2.0.0)
Requires-Dist: opentelemetry-exporter-otlp (>=1.11,<2.0.0)
Requires-Dist: opentelemetry-instrumentation-aws-lambda (>=0.57b0,<0.58)
Requires-Dist: opentelemetry-instrumentation-botocore (>=0.57b0,<0.58)
Requires-Dist: opentelemetry-instrumentation-django (>=0.57b0,<0.58)
Requires-Dist: opentelemetry-instrumentation-fastapi (>=0.57b0,<0.58)
Requires-Dist: opentelemetry-instrumentation-flask (>=0.57b0,<0.58)
Requires-Dist: opentelemetry-instrumentation-logging (>=0.57b0,<0.58)
Requires-Dist: opentelemetry-instrumentation-psycopg2 (>=0.57b0,<0.58)
Requires-Dist: opentelemetry-instrumentation-requests (>=0.57b0,<0.58)
Requires-Dist: opentelemetry-instrumentation-sqlalchemy (>=0.57b0,<0.58)
Requires-Dist: opentelemetry-sdk (>=1.36.0,<2.0.0)
Requires-Dist: protobuf (==3.20.3)
Requires-Dist: psycopg2-binary (>=2.9.10,<3.0.0)
Requires-Dist: starlette (>=0.40.0,<0.47.0)
